<?xml version="1.0" encoding="UTF-8" standalone="no"?>
<Canvas xmlns="http://www.jgrasp.org">
  <Language>Java</Language>
  <ShowTypes>false</ShowTypes>
  <Version>2</Version>
  <Grid>
    <Snap>true</Snap>
    <Show>false</Show>
  </Grid>
  <Frame>
    <Bounds>
      <AutoSize>true</AutoSize>
      <X>520</X>
      <Y>100</Y>
      <W>228</W>
      <H>447</H>
    </Bounds>
    <Viewer>
      <Expression>myItems.inventory</Expression>
      <ViewerClass>_X_ElementView</ViewerClass>
    </Viewer>
  </Frame>
  <Frame>
    <Bounds>
      <AutoSize>true</AutoSize>
      <X>40</X>
      <Y>230</Y>
      <W>312</W>
      <H>145</H>
    </Bounds>
    <Viewer>
      <Expression>myItems</Expression>
      <ViewerClass>java__lang__Object_FormattedToStringView</ViewerClass>
    </Viewer>
  </Frame>
  <Frame>
    <Bounds>
      <AutoSize>false</AutoSize>
      <X>40</X>
      <Y>70</Y>
      <W>398</W>
      <H>98</H>
    </Bounds>
    <PanelSize>
      <Key>_X_ElementView0</Key>
      <Order>4</Order>
      <W>404</W>
      <H>127</H>
    </PanelSize>
    <Viewer>
      <Expression>myItems</Expression>
      <ViewerClass>_X_ElementView</ViewerClass>
    </Viewer>
  </Frame>
  <Size>
    <W>1280</W>
    <H>800</H>
  </Size>
  <ESize>
    <W>640</W>
    <H>644</H>
  </ESize>
</Canvas>
